mipsolver.cp313-win_amd64.pyd
mipsolver_pro-1.0.1.dist-info/METADATA
mipsolver_pro-1.0.1.dist-info/WHEEL
mipsolver_pro-1.0.1.dist-info/top_level.txt
mipsolver_pro-1.0.1.dist-info/RECORD
