Metadata-Version: 2.4
Name: mipsolver-pro
Version: 1.0.1
Summary: High-performance Mixed-Integer Programming solver (Professional Edition)
Home-page: https://github.com/yourusername/MIPSolver
Author: Yutong Lv
Author-email: your.email@example.com
Project-URL: Bug Reports, https://github.com/yourusername/MIPSolver/issues
Project-URL: Source, https://github.com/yourusername/MIPSolver
Project-URL: Documentation, https://mipsolver.readthedocs.io/
Keywords: optimization mip solver integer programming commercial
Classifier: Development Status :: 4 - Beta
Classifier: Intended Audience :: Science/Research
Classifier: License :: Other/Proprietary License
Classifier: Operating System :: Microsoft :: Windows
Classifier: Operating System :: POSIX :: Linux
Classifier: Operating System :: MacOS
Classifier: Programming Language :: Python :: 3
Classifier: Programming Language :: Python :: 3.7
Classifier: Programming Language :: Python :: 3.8
Classifier: Programming Language :: Python :: 3.9
Classifier: Programming Language :: Python :: 3.10
Classifier: Programming Language :: Python :: 3.11
Classifier: Topic :: Scientific/Engineering :: Mathematics
Requires-Python: >=3.7
Requires-Dist: pybind11>=2.6
Dynamic: author
Dynamic: author-email
Dynamic: classifier
Dynamic: description
Dynamic: description-content-type
Dynamic: home-page
Dynamic: keywords
Dynamic: project-url
Dynamic: requires-dist
Dynamic: requires-python
Dynamic: summary
